<?xml version="1.0" encoding="UTF-8"?>
<!-- Add the Send Task Mail button -->
<templates id="template" xml:space="preserve">
    <t t-name="One2manyDelete"
       t-inherit="web.X2ManyField" t-inherit-mode="primary" owl="1">
        <xpath expr="//div[hasclass('o_x2m_control_panel')]" position="inside">
            <div>
                <button t-if="hasSelected" class="btn btn-primary"
                        t-on-click="sendTaskMail"> Send Task Mail
                </button>
                <t t-if="props.readonly">
                    <span class="oe_form_char_content"/>
                </t>
            </div>
        </xpath>
    </t>
</templates>
